pip_download/__init__.py
pip_download/cli.py
pip_download/pip_downloader.py
pip_download/utils/__init__.py
pip_download/utils/cli_helpers.py
pip_download/utils/download_file.py
pip_download/utils/wheel.py
cloudshell_pip_download-0.5.1.dist-info/METADATA
cloudshell_pip_download-0.5.1.dist-info/WHEEL
cloudshell_pip_download-0.5.1.dist-info/entry_points.txt
cloudshell_pip_download-0.5.1.dist-info/top_level.txt
cloudshell_pip_download-0.5.1.dist-info/RECORD
