Metadata-Version: 2.1
Name: cloudshell-pip-download
Version: 0.5.1
Summary: downloads python packages for specified platform and python version
Home-page: UNKNOWN
Author: Kyrylo Maksymenko
Author-email: saklar13@gmail.com
License: UNKNOWN
Platform: UNKNOWN
Requires-Python: ~=3.7
Requires-Dist: click (~=8.0)
Requires-Dist: pip-tools (~=6.2)
Requires-Dist: pip (<22,>=20.3)
Requires-Dist: tqdm (~=4.53)
Requires-Dist: packaging (<22,>=20.4)
